setup.py
trend_following.c
utils.py
trend_following_frd.egg-info/PKG-INFO
trend_following_frd.egg-info/SOURCES.txt
trend_following_frd.egg-info/dependency_links.txt
trend_following_frd.egg-info/requires.txt
trend_following_frd.egg-info/top_level.txt