Metadata-Version: 2.4
Name: trend_following_frd
Version: 1.0
Summary: Módulo de backtest de trend following en C
Requires-Python: >=3.6
Requires-Dist: numpy
Requires-Dist: pandas
Dynamic: requires-dist
Dynamic: requires-python
Dynamic: summary
